README
setup.py
PyMessager.egg-info/PKG-INFO
PyMessager.egg-info/SOURCES.txt
PyMessager.egg-info/dependency_links.txt
PyMessager.egg-info/requires.txt
PyMessager.egg-info/top_level.txt
pymessager/__init__.py
pymessager/message.py