Metadata-Version: 1.0
Name: PyMessager
Version: 1.0.1
Summary: A Python SDK and Flask API to develop Facebook Messenger application
Home-page: https://github.com/enginebai/PyMessager
Author: Engine Bai
Author-email: enginebai@gmail.com
License: The MIT License (MIT) Copyright © 2017 Engine Bai.
Platform: UNKNOWN
